[{"mid": "4693944782815563", "reposts": 0, "comments": 0, "attitudes": 0, "uid": "6648497407", "followers": 543000}, {"mid": "4693944635492248", "reposts": 0, "comments": 0, "attitudes": 0, "uid": "2441892297", "followers": 9962}, {"mid": "4693944119591071", "reposts": 9, "comments": 3, "attitudes": 7, "uid": "2076215147", "followers": 232000}, {"mid": "4693940798752326", "reposts": 2, "comments": 18, "attitudes": 182, "uid": "7021849916", "followers": 767000}, {"mid": "4693938609587427", "reposts": 0, "comments": 3, "attitudes": 0, "uid": "1285766055", "followers": 1147000}, {"mid": "4693936842735796", "reposts": 1434, "comments": 821, "attitudes": 12825, "uid": "2367031834", "followers": 1038000}, {"mid": "4693935727314871", "reposts": 13, "comments": 16, "attitudes": 603, "uid": "7149204657", "followers": 799000}, {"mid": "4693931390929132", "reposts": 2, "comments": 5, "attitudes": 250, "uid": "7021849916", "followers": 767000}]