[{"mid": "4700588635849490", "reposts": 2, "comments": 2, "attitudes": 0, "uid": "1763950617", "followers": 903952}, {"mid": "4700580562076064", "reposts": 12, "comments": 8, "attitudes": 11, "uid": "2556821951", "followers": 368492}, {"mid": "4700580239642690", "reposts": 9, "comments": 4, "attitudes": 6, "uid": "2207254075", "followers": 50991}, {"mid": "4700577851770434", "reposts": 12, "comments": 8, "attitudes": 3, "uid": "1740936973", "followers": 2528167}, {"mid": "4700574664364642", "reposts": 672, "comments": 219, "attitudes": 161, "uid": "1898812267", "followers": 737541}, {"mid": "4700570503614063", "reposts": 1684, "comments": 404, "attitudes": 619, "uid": "2831094660", "followers": 5130863}, {"mid": "4700565475691232", "reposts": 3, "comments": 3, "attitudes": 1, "uid": "2316518354", "followers": 1156647}, {"mid": "4700560903111557", "reposts": 947, "comments": 442, "attitudes": 354, "uid": "5103458366", "followers": 887000}]