[{"mid": "4679584724028419", "reposts": 5, "comments": 1, "attitudes": 2, "uid": "1798143541", "followers": 483518}, {"mid": "4679584312987261", "reposts": 1, "comments": 0, "attitudes": 0, "uid": "3796261850", "followers": 102463}, {"mid": "4679581527708235", "reposts": 13, "comments": 12, "attitudes": 4, "uid": "5082974871", "followers": 841564}, {"mid": "4679580528675181", "reposts": 45, "comments": 24, "attitudes": 17, "uid": "7420344364", "followers": 65907}, {"mid": "4679579602257899", "reposts": 1, "comments": 0, "attitudes": 1, "uid": "5666880448", "followers": 57261}, {"mid": "4679577403918722", "reposts": 5, "comments": 1, "attitudes": 0, "uid": "3971315482", "followers": 270643}, {"mid": "4679577349130432", "reposts": 5, "comments": 3, "attitudes": 3, "uid": "7549609668", "followers": 96680}, {"mid": "4679577241129089", "reposts": 5, "comments": 20, "attitudes": 14, "uid": "7095404909", "followers": 10052431}]