[{"mid": "4688216122986425", "reposts": 41, "comments": 7, "attitudes": 15, "uid": "1798143541", "followers": 485675}, {"mid": "4688214087962568", "reposts": 133, "comments": 17, "attitudes": 29, "uid": "2219299801", "followers": 170539}, {"mid": "4688209574889300", "reposts": 9, "comments": 4, "attitudes": 1, "uid": "2310074515", "followers": 52880}, {"mid": "4688208409661229", "reposts": 29, "comments": 32, "attitudes": 21, "uid": "3314422837", "followers": 2018463}, {"mid": "4688199865336783", "reposts": 133, "comments": 37, "attitudes": 54, "uid": "1769962140", "followers": 5079494}, {"mid": "4688199786432361", "reposts": 60, "comments": 34, "attitudes": 14, "uid": "5693194807", "followers": 2719619}, {"mid": "4688199207879746", "reposts": 14, "comments": 27, "attitudes": 16, "uid": "7095404909", "followers": 10074247}, {"mid": "4688187534870069", "reposts": 13, "comments": 15, "attitudes": 17, "uid": "2601297945", "followers": 752828}]