[{"mid": "4681064888403160", "reposts": 0, "comments": 0, "attitudes": 0, "uid": "1658272290", "followers": 104708}, {"mid": "4681064473168631", "reposts": 0, "comments": 1, "attitudes": 0, "uid": "1655035324", "followers": 86134}, {"mid": "4681056924472781", "reposts": 0, "comments": 0, "attitudes": 0, "uid": "6530179529", "followers": 81725}, {"mid": "4681056924210355", "reposts": 0, "comments": 0, "attitudes": 0, "uid": "7293597831", "followers": 44224}, {"mid": "4681056407521227", "reposts": 193, "comments": 250, "attitudes": 153, "uid": "1454338611", "followers": 3094958}, {"mid": "4681054294901841", "reposts": 9, "comments": 7, "attitudes": 3, "uid": "1829065134", "followers": 4718}, {"mid": "4681048435196482", "reposts": 9, "comments": 6, "attitudes": 8, "uid": "3032417477", "followers": 51329}, {"mid": "4681043872055319", "reposts": 3314, "comments": 1824, "attitudes": 6024, "uid": "1761587065", "followers": 3466306}]