[{"mid": "4690078750216069", "reposts": 2, "comments": 2, "attitudes": 3, "uid": "7675460805", "followers": 58699}, {"mid": "4690078544432010", "reposts": 6, "comments": 4, "attitudes": 3, "uid": "6245953813", "followers": 115177}, {"mid": "4690078134439391", "reposts": 15, "comments": 10, "attitudes": 4, "uid": "6433763027", "followers": 738055}, {"mid": "4690078003364503", "reposts": 3, "comments": 3, "attitudes": 0, "uid": "1707486362", "followers": 513239}, {"mid": "4690077840049907", "reposts": 29, "comments": 5, "attitudes": 10, "uid": "5186845471", "followers": 620771}, {"mid": "4690076439415440", "reposts": 1, "comments": 1, "attitudes": 0, "uid": "6982915682", "followers": 773571}, {"mid": "4690076111734601", "reposts": 15, "comments": 10, "attitudes": 13, "uid": "1988033715", "followers": 744029}, {"mid": "4690075416529362", "reposts": 1, "comments": 1, "attitudes": 1, "uid": "7442212008", "followers": 201396}]