[{"mid": "4696172985320553", "reposts": 367, "comments": 7410, "attitudes": 2653, "uid": "5586965954", "followers": 5543269}, {"mid": "4696171149265947", "reposts": 46, "comments": 8, "attitudes": 6, "uid": "6722242295", "followers": 58923}, {"mid": "4696166085693162", "reposts": 3547, "comments": 88, "attitudes": 26, "uid": "2907866145", "followers": 24928}, {"mid": "4696158926799510", "reposts": 58, "comments": 24, "attitudes": 10, "uid": "1979535124", "followers": 1005164}, {"mid": "4696156409432157", "reposts": 0, "comments": 1, "attitudes": 0, "uid": "2117187644", "followers": 1266345}, {"mid": "4696156413629811", "reposts": 16, "comments": 6, "attitudes": 5, "uid": "1051008504", "followers": 318135}, {"mid": "4696153570937982", "reposts": 34, "comments": 15, "attitudes": 12, "uid": "1769962140", "followers": 5079548}, {"mid": "4696151674847658", "reposts": 31, "comments": 20, "attitudes": 12, "uid": "1988033715", "followers": 745033}]