[{"mid": "4693356750572965", "reposts": 0, "comments": 0, "attitudes": 0, "uid": "6123203601", "followers": 1008771}, {"mid": "4693355893886536", "reposts": 1, "comments": 1, "attitudes": 3, "uid": "3032417477", "followers": 51611}, {"mid": "4693353226830139", "reposts": 21, "comments": 11, "attitudes": 11, "uid": "5710169818", "followers": 2295382}, {"mid": "4693349393762443", "reposts": 0, "comments": 30, "attitudes": 506, "uid": "6494237922", "followers": 2935523}, {"mid": "4693335309288325", "reposts": 59, "comments": 20, "attitudes": 53, "uid": "2710257782", "followers": 1039706}, {"mid": "4693332804764396", "reposts": 16, "comments": 14, "attitudes": 7, "uid": "1653150175", "followers": 349000}, {"mid": "4693331642417588", "reposts": 3, "comments": 3, "attitudes": 2, "uid": "7191493255", "followers": 50584}, {"mid": "4693326248543849", "reposts": 0, "comments": 32, "attitudes": 8, "uid": "3225670881", "followers": 2126744}]