[{"mid": "4691965481846892", "reposts": 0, "comments": 4, "attitudes": 96, "uid": "7021849916", "followers": 766509}, {"mid": "4691964362493025", "reposts": 2019, "comments": 2, "attitudes": 1294, "uid": "1897261013", "followers": 5403159}, {"mid": "4691956448625849", "reposts": 0, "comments": 11, "attitudes": 295, "uid": "7021849916", "followers": 766509}, {"mid": "4691955348671633", "reposts": 3, "comments": 1, "attitudes": 3, "uid": "6758330187", "followers": 899285}, {"mid": "4691940786833253", "reposts": 0, "comments": 4, "attitudes": 7, "uid": "1307665573", "followers": 1752386}, {"mid": "4691938723496627", "reposts": 25, "comments": 520, "attitudes": 97, "uid": "6059201059", "followers": 57000}, {"mid": "4691936106254037", "reposts": 5, "comments": 2, "attitudes": 7, "uid": "2696981251", "followers": 20528}, {"mid": "4691935103029071", "reposts": 17, "comments": 707, "attitudes": 243, "uid": "3894844112", "followers": 1348466}]