[{"mid": "4676407219717128", "reposts": 986, "comments": 600, "attitudes": 334, "uid": "6114830371", "followers": 760211}, {"mid": "4676406301164207", "reposts": 51, "comments": 133, "attitudes": 48, "uid": "2128589743", "followers": 142077}, {"mid": "4676394757652773", "reposts": 1, "comments": 49, "attitudes": 22, "uid": "6633844596", "followers": 625698}, {"mid": "4676368396196684", "reposts": 113, "comments": 3870, "attitudes": 570, "uid": "1757573407", "followers": 4976735}, {"mid": "4676361181990064", "reposts": 905, "comments": 259, "attitudes": 444, "uid": "5861184617", "followers": 2530217}, {"mid": "4676360980925924", "reposts": 10, "comments": 6, "attitudes": 6, "uid": "6016015458", "followers": 737124}, {"mid": "4676357600838727", "reposts": 17, "comments": 51, "attitudes": 18, "uid": "1660521332", "followers": 6696109}, {"mid": "4676356334164003", "reposts": 263, "comments": 64, "attitudes": 48, "uid": "1769962140", "followers": 5077740}]