[{"mid": "4707715223651506", "reposts": 1, "comments": 1, "attitudes": 1, "uid": "1751216954", "followers": 336672}, {"mid": "4707715073706614", "reposts": 0, "comments": 1, "attitudes": 0, "uid": "1770038852", "followers": 186833}, {"mid": "4707712288686861", "reposts": 45, "comments": 14, "attitudes": 10, "uid": "1420174783", "followers": 6129611}, {"mid": "4707685209997880", "reposts": 1141, "comments": 572, "attitudes": 551, "uid": "3808007273", "followers": 5459086}, {"mid": "4707578241877859", "reposts": 1, "comments": 103, "attitudes": 330, "uid": "5744916923", "followers": 621132}, {"mid": "4707564706598975", "reposts": 0, "comments": 3, "attitudes": 212, "uid": "7021849916", "followers": 769000}, {"mid": "4707561272509739", "reposts": 0, "comments": 15, "attitudes": 10, "uid": "6633844596", "followers": 661248}, {"mid": "4707557362633797", "reposts": 183, "comments": 199, "attitudes": 534, "uid": "2576867470", "followers": 10022000}]