[{"mid": "4707397983014443", "reposts": 0, "comments": 0, "attitudes": 0, "uid": "3928511449", "followers": 1674913}, {"mid": "4707390723723156", "reposts": 106, "comments": 98, "attitudes": 35, "uid": "2036665107", "followers": 30556}, {"mid": "4707390454235574", "reposts": 65, "comments": 26, "attitudes": 9, "uid": "7462764041", "followers": 7928}, {"mid": "4707390446636923", "reposts": 4, "comments": 4, "attitudes": 2, "uid": "1674122465", "followers": 782000}, {"mid": "4707390446111066", "reposts": 55, "comments": 9, "attitudes": 10, "uid": "2219299801", "followers": 180000}, {"mid": "4707390441655114", "reposts": 0, "comments": 0, "attitudes": 0, "uid": "6332186984", "followers": 165000}, {"mid": "4707390437462429", "reposts": 46, "comments": 17, "attitudes": 13, "uid": "1704709632", "followers": 1021000}, {"mid": "4707390437458150", "reposts": 6, "comments": 4, "attitudes": 1, "uid": "2678510271", "followers": 434484}]