[{"mid": "4690106504185784", "reposts": 0, "comments": 4, "attitudes": 106, "uid": "7021849916", "followers": 766556}, {"mid": "4690101520831345", "reposts": 5, "comments": 1, "attitudes": 0, "uid": "5684610880", "followers": 42073}, {"mid": "4690088791117090", "reposts": 296, "comments": 143, "attitudes": 51, "uid": "6072478686", "followers": 2681622}, {"mid": "4690086430508117", "reposts": 1, "comments": 1, "attitudes": 2, "uid": "2253887482", "followers": 293102}, {"mid": "4690086421071739", "reposts": 2, "comments": 2, "attitudes": 0, "uid": "7567951501", "followers": 303}, {"mid": "4690083867267418", "reposts": 12, "comments": 8, "attitudes": 33, "uid": "1761178540", "followers": 224619}, {"mid": "4690083360016601", "reposts": 40, "comments": 29, "attitudes": 15, "uid": "6141049891", "followers": 153312}, {"mid": "4690078750216069", "reposts": 18, "comments": 16, "attitudes": 11, "uid": "7675460805", "followers": 58725}]