[{"mid": "4691263968510683", "reposts": 2, "comments": 24, "attitudes": 18, "uid": "6633844596", "followers": 652702}, {"mid": "4691252820312193", "reposts": 1, "comments": 13, "attitudes": 143, "uid": "7021849916", "followers": 766461}, {"mid": "4691249925462812", "reposts": 8, "comments": 39, "attitudes": 31, "uid": "5647901081", "followers": 58495}, {"mid": "4691244834622835", "reposts": 7, "comments": 138, "attitudes": 28, "uid": "2660358043", "followers": 976312}, {"mid": "4691243625876724", "reposts": 1, "comments": 169, "attitudes": 91, "uid": "3917019574", "followers": 694028}, {"mid": "4691227955430264", "reposts": 336, "comments": 77, "attitudes": 84, "uid": "5250110568", "followers": 452313}, {"mid": "4691213761909176", "reposts": 42, "comments": 251, "attitudes": 3057, "uid": "5870071346", "followers": 1138408}, {"mid": "4691200046794670", "reposts": 296, "comments": 2536, "attitudes": 3683, "uid": "5698023579", "followers": 13871186}]