[{"mid": "4680835972989360", "reposts": 0, "comments": 0, "attitudes": 0, "uid": "6074394293", "followers": 1332102}, {"mid": "4680724596394710", "reposts": 357, "comments": 113, "attitudes": 142, "uid": "5132930861", "followers": 2164305}, {"mid": "4680716274897174", "reposts": 1, "comments": 36, "attitudes": 11, "uid": "2148448820", "followers": 817636}, {"mid": "4680715679826591", "reposts": 0, "comments": 0, "attitudes": 0, "uid": "3032417477", "followers": 51324}, {"mid": "4680711125074109", "reposts": 100, "comments": 20, "attitudes": 16, "uid": "1410812623", "followers": 5166481}, {"mid": "4680710008868805", "reposts": 491, "comments": 77, "attitudes": 111, "uid": "1423850780", "followers": 5293829}, {"mid": "4680709366875050", "reposts": 1890, "comments": 1350, "attitudes": 3361, "uid": "2809841193", "followers": 9551748}, {"mid": "4680702534619043", "reposts": 2, "comments": 10, "attitudes": 500, "uid": "2253566775", "followers": 2249801}]