[{"mid": "4676043119792125", "reposts": 0, "comments": 0, "attitudes": 0, "uid": "5102253217", "followers": 1161091}, {"mid": "4676041798585139", "reposts": 2, "comments": 31, "attitudes": 18, "uid": "6633844596", "followers": 624276}, {"mid": "4676034152894594", "reposts": 50, "comments": 23, "attitudes": 24, "uid": "1394997154", "followers": 722848}, {"mid": "4676023217816900", "reposts": 8, "comments": 0, "attitudes": 2, "uid": "1665003262", "followers": 101367}, {"mid": "4676018654152006", "reposts": 13, "comments": 6, "attitudes": 5, "uid": "3169179383", "followers": 147383}, {"mid": "4676000387957352", "reposts": 8, "comments": 107, "attitudes": 41, "uid": "2264713730", "followers": 4516897}, {"mid": "4675993644827323", "reposts": 91, "comments": 39, "attitudes": 193, "uid": "2647509761", "followers": 1752083}, {"mid": "4675990200520075", "reposts": 508, "comments": 174, "attitudes": 238, "uid": "1563458343", "followers": 3023089}]