[{"mid": "4682798054508256", "reposts": 22, "comments": 17, "attitudes": 13, "uid": "2789987841", "followers": 3298186}, {"mid": "4682796042029218", "reposts": 32, "comments": 67, "attitudes": 27, "uid": "5727858471", "followers": 829819}, {"mid": "4682792850162040", "reposts": 33, "comments": 30, "attitudes": 42, "uid": "2583592444", "followers": 1979465}, {"mid": "4682791776947884", "reposts": 23, "comments": 12, "attitudes": 11, "uid": "5987108147", "followers": 1235358}, {"mid": "4682791155401006", "reposts": 4, "comments": 3, "attitudes": 2, "uid": "1318041143", "followers": 5526}, {"mid": "4682784423021424", "reposts": 6, "comments": 3, "attitudes": 0, "uid": "5652911346", "followers": 1243194}, {"mid": "4682783841322538", "reposts": 49, "comments": 31, "attitudes": 27, "uid": "7418748829", "followers": 21614}, {"mid": "4682782988567831", "reposts": 0, "comments": 18, "attitudes": 6, "uid": "2850640164", "followers": 361090}]