[{"title": "\uff08\u7f8e\u7d20\u4f73\u513f\uff09\u5fae\u4fe1\u7ea2\u5305 \u76ee\u524d\u8c8c\u4f3c\u5fc5\u4e2d", "content": "<p><a href=\"http://x9uwm.cn/1SMvV\">http://x9uwm.cn/1SMvV</a>\n\u5fae\u4fe1\u6253\u5f00\u4e71\u4f20\u56fe\u7247 \u6700\u540e\u70b9\u9886\u53d6\n\u76ee\u524d\u8c8c\u4f3c\u5fc5\u4e2d\u96f6\u94b1</p>\n<pre><img alt=\"\uff08\u7f8e\u7d20\u4f73\u513f\uff09\u5fae\u4fe1\u7ea2\u5305 \u76ee\u524d\u8c8c\u4f3c\u5fc5\u4e2d\" src=\"https://osszrbimg.zrb.net/cirheadimg/202106/c0607c9f-4369-4b3c-95c0-e75c5f5f8e7b400x800.jpg\"/></pre>\n<p></p>\n<pre><img alt=\"\uff08\u7f8e\u7d20\u4f73\u513f\uff09\u5fae\u4fe1\u7ea2\u5305 \u76ee\u524d\u8c8c\u4f3c\u5fc5\u4e2d\" src=\"https://osszrbimg.zrb.net/cirheadimg/202106/3fba05f6-0112-4443-a2ab-46dbcd27527c400x800.jpg\"/></pre>", "time": 1624512964}, {"title": "\n\u514d\u8d39\u9886\u7f51\u6613\u4e91\u97f3\u4e50\u9ed1\u80f6\u4f1a\u5458VIP\u5361 ", "content": "<p><a href=\"https://69fl.cn/wp-content/uploads/2021/06/6615.jpg\"><img alt=\"\" class=\"alignnone size-full wp-image-6616 img-lazyload\" src=\"https://69fl.cn/wp-content/uploads/2021/06/6615.jpg\" height=\"903\" loading=\"lazy\"  width=\"1670\"/></a></p>\n<p>\u514d\u8d39\u9886\u7f51\u6613\u4e91\u97f3\u4e50\u9ed1\u80f6\u4f1a\u5458VIP\u5361\uff0c\u9080\u597d\u53cb\u6700\u591a\u98862\u4e2a\u6708\u54e6\uff01</p>\n<p>\u6253\u5f00\u6700\u65b0\u7248\u7f51\u6613\u4e91\u97f3\u4e50App -&gt; \u641c\u7d22\u201c\u5237\u5237\u4e50\u201d-&gt; \u70b9\u5237\u97f3\u4e50\u89c6\u9891\u8fdb\u53bb\u53c2\u52a0 -&gt; \u4e0b\u62c9\u9875\u9762\u5b8c\u62103\u4e2a\u4efb\u52a1\u62bd\u5956 -&gt; \u6bcf\u5929\u90fd\u53ef\u4ee5\u53c2\u52a0</p>\n<p>\u7136\u540e\u518d\u641c\u7d22\u201c\u4e00\u8d77\u542c\u201d-&gt; \u641c\u51fa\u6765\u540e\u70b9\u4e0b\u9762\u5206\u4eab\u4e00\u8d77\u542c\u8fdb\u53bb\u53c2\u52a0 -&gt; \u9080\u597d\u53cb\u53ef\u988652\u5929\u4f1a\u5458\uff08\u524d\u97623\u6b21\u662f\u5468\u5361\uff0c\u6700\u540e\u4e00\u6b21\u662f\u6708\u5361\uff09</p>\n<p>\u5237\u5237\u4e50\uff1a<a href=\"https://music.163.com/m/at/60cb103d6000b3c12be5db6c\" rel=\"noopener\" target=\"_blank\">https://music.163.com/m/at/60cb103d6000b3c12be5db6c</a></p>\n<p>\u4e00\u8d77\u542c\uff1a<a href=\"https://music.163.com/m/at/60d1e073d35d9462e2b17da0?inviterId=92508010&amp;code=98AEB488B1E82A2EFD530ED44996C80E&amp;nickname=%E6%B1%B6%E6%B5%B7%E6%B4%B3\" rel=\"noopener\" target=\"_blank\">https://music.163.com/m/at/60d1dccdeb696871a519264f</a></p>", "time": 1624519409}, {"title": "\uff08\u65b0\u7f57\u533a\u77e5\u8bc6\u7ade\u8d5b\uff09\u975e\u5fc5\u4e2d\uff01", "content": "<p><a href=\"http://w.duanlm.com/yPAa3\">http://w.duanlm.com/yPAa3</a>\n\u51e1\u7b80\u5355\u7b54\u9898\u901f\u5ea6\u53bb\uff0c\u4e2d\u8fc7\u7684\u4e5f\u53bb\u8bd5\u8bd5  \u4eb2\u6d4b\n\u7b54\u684823121413   </p>\n<pre><img alt=\"\uff08\u65b0\u7f57\u533a\u77e5\u8bc6\u7ade\u8d5b\uff09\u975e\u5fc5\u4e2d\uff01\" src=\"https://osszrbimg.zrb.net/cirheadimg/202106/eb9584cd-c1ba-4887-85ee-6d939df18bad400x800.jpg\"/></pre>", "time": 1624548959}, {"title": "\u3010\u4e1c\u8425\u5de5\u4f1a\u670d\u52a1\u53f7\u3011\u5fae\u4fe1\u7ea2\u5305 \u975e\u5fc5\u4e2d", "content": "<p>\u5fae\u4fe1\u6253\u5f00 5\u9898\u5168\u5bf9\u62bd \n<a href=\"https://e554944425683.fengchuanba.com/index.html#554944425683-UQ99nqmwn6bOjGgphwc1rjWToPyanMgM\">https://e554944425683.fengchuanba.com/index.html#554944425683-UQ99nqmwn6bOjGgphwc1rjWToPyanMgM</a>\n\n\u9898\u76ee\u7b54\u6848\n<a href=\"http://x9uwm.cn/5iBKO\">http://x9uwm.cn/5iBKO</a></p>\n<pre><img alt=\"\u3010\u4e1c\u8425\u5de5\u4f1a\u670d\u52a1\u53f7\u3011\u5fae\u4fe1\u7ea2\u5305 \u975e\u5fc5\u4e2d\" src=\"https://osszrbimg.zrb.net/cirheadimg/202106/6f010b1c-1cc0-455d-8659-8f64268f37db400x800.jpg\"/></pre>", "time": 1624548954}, {"title": "\n\u638c\u4e0a\u751f\u6d3b\u514d\u8d39\u9886\u817e\u8baf\u89c6\u9891\u4f1a\u5458\u6708\u5361 ", "content": "<p><a href=\"https://69fl.cn/wp-content/uploads/2021/06/6609.jpg\"><img alt=\"\" class=\"alignnone size-full wp-image-6610 img-lazyload\" src=\"https://69fl.cn/wp-content/uploads/2021/06/6609.jpg\" height=\"939\" loading=\"lazy\"  width=\"1300\"/></a></p>\n<p>\u9650 6.1 - 6.17 \u672a\u767b\u5f55\u8fc7\u7684\u8001\u7528\u6237\u9886\u53d6\uff01\u817e\u8baf\u89c6\u9891\u4f1a\u5458\u6708\u5361\u6216\u8005 10 \u5143\u8fd8\u6b3e\u91d1~</p>\n<p>\u5148\u6253\u5f00\u767b\u5f55\u638c\u4e0a\u751f\u6d3bAPP\uff0c\u7136\u540e\u518d\u6253\u5f00\u6d3b\u52a8\u5730\u5740\u70b9\u51fb\u9a6c\u4e0a\u53c2\u4e0e\uff0c\u5c31\u4f1a\u8df3\u8f6c\u5230APP\u4e8c\u9009\u4e00\u9886\u53d6\u5373\u53ef\uff0c\u67e5\u770b\u4f18\u60e0\u5238\u590d\u5236\u5238\u7801\u5151\u6362\u5373\u53ef\uff01</p>\n<p>\u9996\u767b\u7528\u6237\u9886\u817e\u8baf\u89c6\u9891\u4f1a\u5458\uff1a<a href=\"https://tb3.cn/AsuFpD\" rel=\"noopener\" target=\"_blank\">https://tb3.cn/AsuFpD</a></p>\n<p>\u817e\u8baf\u89c6\u9891\u4f1a\u5458\u5151\u6362\u5730\u5740\uff1a<a href=\"https://tb3.cn/AVIw3F\" rel=\"noopener\" target=\"_blank\">https://tb3.cn/AVIw3F</a></p>\n<p>\u7279\u9080\u7528\u6237\u98862+3\u5143\u8fd8\u6b3e\u91d1\uff1a<a href=\"https://tb3.cn/ASgFpj\" rel=\"noopener\" target=\"_blank\">https://tb3.cn/ASgFpj</a></p>\n<p>\u6d3b\u52a8\u65f6\u95f4\uff1a2021.6.18~6.30</p>", "time": 1624458110}, {"title": "\u3010\u653b\u57ce\u77f3\u3011\u5fae\u4fe1\u7ea2\u5305\u975e\u5fc5\u4e2d", "content": "<p>\u5fae\u4fe1\u6253\u5f00\uff0c\u653b\u57ce\u77f3\u65b0\u4e00\u671f\u62bd\u5956\uff0c\u76f4\u8fbe\u94fe\u63a5\uff1a<a href=\"https://weixin.midea.com/apps/h5-pro-wx-lucky-draw/index.html?gameId=4542&amp;spreadClass=0&amp;appId=wx993981b5d1d6ad42&amp;channelId=4791&amp;fromSite=1&amp;mpType=ENGINEER#/?old=%2F\">https://weixin.midea.com/apps/h5-pro-wx-lucky-draw/index.html?gameId=4542&amp;spreadClass=0&amp;appId=wx993981b5d1d6ad42&amp;channelId=4791&amp;fromSite=1&amp;mpType=ENGINEER#/?old=%2F</a></p>\n<pre><img alt=\"\u3010\u653b\u57ce\u77f3\u3011\u5fae\u4fe1\u7ea2\u5305\u975e\u5fc5\u4e2d\" src=\"https://osszrbimg.zrb.net/cirheadimg/202106/50e2c815-7cec-4c72-ae2b-5192f977b53b400x800.jpg\"/></pre>\n<p></p>\n<pre><img alt=\"\u3010\u653b\u57ce\u77f3\u3011\u5fae\u4fe1\u7ea2\u5305\u975e\u5fc5\u4e2d\" src=\"https://osszrbimg.zrb.net/cirheadimg/202106/4aabe942-d8d7-4464-8af0-2d003a5750be400x800.jpg\"/></pre>\n<p></p>\n<pre><img alt=\"\u3010\u653b\u57ce\u77f3\u3011\u5fae\u4fe1\u7ea2\u5305\u975e\u5fc5\u4e2d\" src=\"https://osszrbimg.zrb.net/cirheadimg/202106/0667eb34-3c22-4c37-976a-093bca3c979d400x800.jpg\"/></pre>", "time": 1624548949}, {"title": "\u3010\u62db\u5546\u4fe1\u8bfa\u3011\u7ea2\u5305\u5fc5\u4e2d\u9650\u91cf", "content": "<p>\u5fae\u4fe1\u5173\u6ce8\u3010\u62db\u5546\u4fe1\u8bfa\u3011\uff0c\u56de\u590d\u3010\u593a\u5b9d\u3011/\u3010\u7ea2\u5305\u3011/\u3010\u4e00\u8bfa\u4e07\u91d1\u3011\uff0c\u4e09\u4e2a\u53e3\u4ee4\u90fd\u8bd5\u8bd5\uff0c\u76ee\u524d\u5fc5\u4e2d\u7ea2\u5305</p>\n<pre><img alt=\"\u3010\u62db\u5546\u4fe1\u8bfa\u3011\u7ea2\u5305\u5fc5\u4e2d\u9650\u91cf\" src=\"https://osszrbimg.zrb.net/cirheadimg/202106/d786ef24-345a-484b-aa85-82f3e25e7701400x800.jpg\"/></pre>", "time": 1624548944}, {"title": "\n\u6ef4\u6ef4\u51fa\u884c\u52a9\u529b\u9886\u53d68~32\u5143\u7ea2\u5305 ", "content": "<p><a href=\"https://69fl.cn/wp-content/uploads/2021/06/6592.jpg\"><img alt=\"\" class=\"alignnone size-full wp-image-6593 img-lazyload\" src=\"https://69fl.cn/wp-content/uploads/2021/06/6592.jpg\" height=\"933\" loading=\"lazy\"  width=\"1300\"/></a></p>\n<p>\u5fae\u4fe1\u5c0f\u7a0b\u5e8f\u641c\u7d22\u201c\u6ef4\u6ef4\u51fa\u884c\u201d-&gt;\u70b9\u798f\u5229\u4e2d\u5fc3-&gt;\u4e0b\u62c9\u9875\u9762\u627e\u5230\u201c\u5bfb\u627e\u597d\u53cb\u52a9\u529b\uff0c\u5f978\u5143\u73b0\u91d1\u201d</p>\n<p>\u8fdb\u6765\u90804\u4e2a120\u5929\u672a\u6253\u8f66\u6216\u8005\u65b0\u4eba\u52a9\u529b\u5373\u53ef\u83b7\u5f97\uff0824\u5c0f\u65f6\u5185\u5230\uff09-&gt;\u6d3b\u52a8\u65f6\u95f4\u5185\u6bcf\u5929\u53ef\u53c2\u52a01\u6b21\uff01</p>\n<p>\u6d3b\u52a8\u65f6\u95f4\uff1a2021.6.21~6.24</p>", "time": 1624338269}, {"title": "\n\u5168\u56fd\u533b\u62a4\u4eba\u5458\u4eca\u65e5\u514d\u8d39\u559d\u559c\u8336 ", "content": "<p><a href=\"https://69fl.cn/wp-content/uploads/2021/06/6589.jpg\"><img alt=\"\" class=\"alignnone size-full wp-image-6590 img-lazyload\" src=\"https://69fl.cn/wp-content/uploads/2021/06/6589.jpg\" height=\"788\" loading=\"lazy\"  width=\"1749\"/></a></p>\n<p>\u81f4\u656c\u6297\u75ab\u5de5\u4f5c\u8005</p>\n<p>\u5168\u56fd\u533b\u62a4\u4eba\u5458\u53ef\u572822\u65e5\u5f53\u5929\u51ed\u8bc1\u5728\u559c\u8336\u95e8\u5e97\u514d\u8d39\u9886\u53d6\u4e00\u676f\u829d\u829d\u8317\u8336\uff0c\u4e0d\u7b26\u5408\u7684\u53ef\u4ee5\u8f6c\u7ed9\u8eab\u8fb9\u7684\u533b\u62a4\u4eba\u5458\uff01</p>\n<p>\u6d3b\u52a8\u8bf4\u660e\uff1a<a href=\"https://mp.weixin.qq.com/s/5ttVxwn7HvswJhrCZ0HRqA\" rel=\"noopener\" target=\"_blank\">https://mp.weixin.qq.com/s/5ttVxwn7HvswJhrCZ0HRqA</a></p>", "time": 1624326883}, {"title": "\uff08\u590d\u5229\u8005\u8054\u76df\uff09\u5fc5\u4e2d\uff01", "content": "<p>\u652f\u4ed8\u5b9d\u6253\u5f00\u641c\u7d22\u590d\u5229\u8005\u8054\u76df\n</p>\n<pre><img alt=\"\uff08\u590d\u5229\u8005\u8054\u76df\uff09\u5fc5\u4e2d\uff01\" src=\"https://osszrbimg.zrb.net/cirheadimg/202106/e0458497-a367-408f-920e-f87b968a6ba3400x800.jpg\"/></pre>\n<p>\u56fe\u4e2d\u753b\u5708\u7684\u5730\u65b9\u70b9\u4eae\u4f1a\u9886\u5230\u7ea2\u5305\uff0c\u6bcf\u4e2a0.1\uff0c\u4eb2\u6d4b\u9886\u5bfc0.6\u5143</p>\n<pre><img alt=\"\uff08\u590d\u5229\u8005\u8054\u76df\uff09\u5fc5\u4e2d\uff01\" src=\"https://osszrbimg.zrb.net/cirheadimg/202106/950dc491-359d-4ce8-8f0b-7b79503ad63c400x800.jpg\"/></pre>\n<p>\u5927\u53f7\u8f6c\u5c0f\u53f7\u76f4\u63a5\u5957\u73b0\u91d1\uff0c\u6216\u8005\u81ea\u5df1\u6d88\u8d39\u4f7f\u7528\u90fd\u4f1a\u76f4\u63a5\u62b5\u6263</p>\n<pre><img alt=\"\uff08\u590d\u5229\u8005\u8054\u76df\uff09\u5fc5\u4e2d\uff01\" src=\"https://osszrbimg.zrb.net/cirheadimg/202106/cc7c0fc3-1693-427a-815b-37b66f9c165a400x800.png\"/></pre>", "time": 1624548937}, {"title": "\u3010\u6c34\u7f8e\u8d35\u5dde\u3011\u7ea2\u5305 \u975e\u5fc5\u4e2d", "content": "<p>\u5fae\u4fe1\u5173\u6ce8\u6c34\u7f8e\u8d35\u5dde\u516c\u4f17\u53f7\uff0c\u83dc\u5355\u680f\u6709\u5956\u7b54\u9898\uff0c5\u5bf93\u62bd\u5956</p>\n<pre><img alt=\"\u3010\u6c34\u7f8e\u8d35\u5dde\u3011\u7ea2\u5305 \u975e\u5fc5\u4e2d\" src=\"https://osszrbimg.zrb.net/cirheadimg/202106/5859789b-3381-4a5a-91d6-5ea26b27c344400x800.jpg\"/></pre>\n<p>\n\u4eb2\u6d4b\u4e2d\u4e86\u79d2\u5230\uff01</p>\n<pre><img alt=\"\u3010\u6c34\u7f8e\u8d35\u5dde\u3011\u7ea2\u5305 \u975e\u5fc5\u4e2d\" src=\"https://osszrbimg.zrb.net/cirheadimg/202106/2faa0e7e-3f5c-42a9-a349-7706a2f03fe1400x800.jpg\"/></pre>", "time": 1624548932}, {"title": "\u3010\u4f4f\u5efa\u4e1a\u3011\u7ea2\u5305\u9650\u91cf \u5fc5\u4e2d", "content": "<p>\u5fae\u4fe1\u641c\u7d22\u4f4f\u5efa\u4e1a\u5c0f\u7a0b\u5e8f\uff0c\u9996\u9875\u63a8\u56fe\u70b9\u8fdb\u53bb\u7b4910\u79d2\u62bd\u5956\uff0c\u6bcf\u592910\u5929\u53d1\u5305\uff0c\u9650\u91cf\u5fc5\u4e2d\uff0c\u523030\u53f7\u7ed3\u675f\uff0c\u4eca\u5929\u6ca1\u9886\u5230\u7684\u53ef\u4ee5\u660e\u592910\u70b9\u9886</p>\n<pre><img alt=\"\u3010\u4f4f\u5efa\u4e1a\u3011\u7ea2\u5305\u9650\u91cf \u5fc5\u4e2d\" src=\"https://osszrbimg.zrb.net/cirheadimg/202106/1cf4c16a-d6b5-4fe8-819a-133a8c733ae1400x800.jpg\"/></pre>\n<p>\u9080\u8bf7\u5c0f\u53f7\u548c\u670b\u53cb\u4e5f\u5f97\u7ea2\u5305\uff0c\u65b0\u53f7\u53ef\u4ee5\u7b49\u4eba\u53d1\u4efb\u52a1</p>\n<pre><img alt=\"\u3010\u4f4f\u5efa\u4e1a\u3011\u7ea2\u5305\u9650\u91cf \u5fc5\u4e2d\" src=\"https://osszrbimg.zrb.net/cirheadimg/202106/def27e4d-d874-43c2-9de6-da758bf7cfae400x800.jpg\"/></pre>", "time": 1624548927}, {"title": "\uff3b\u6cb3\u5317IPTV\u4f1a\u5458\uff3d\u5fae\u4fe1\u7ea2\u5305 \u5fc5\u4e2d", "content": "<p>\u5fae\u4fe1\u5173\u6ce8\uff1a\u6cb3\u5317IPTV\u4f1a\u5458\n\u56de\u590d\uff1a\u542f\u822a\n\u53cd\u590d\u5237 \u76f4\u81f3\u5230\u63a8\u5305</p>\n<pre><img alt=\"\uff3b\u6cb3\u5317IPTV\u4f1a\u5458\uff3d\u5fae\u4fe1\u7ea2\u5305 \u5fc5\u4e2d\" src=\"https://osszrbimg.zrb.net/cirheadimg/202106/692fb39c-ece4-4c80-a325-8c15bee9c5d6400x800.jpg\"/></pre>", "time": 1624289764}, {"title": "\uff08\u53e3\u888b\u4fee\u4ed9\uff09\u5fc5\u4e2d\uff01", "content": "<p>\u5fae\u4fe1\u641c\u7d22\u5c0f\u7a0b\u5e8f\uff08\u53e3\u888b\u4fee\u4ed9\uff09\u8fdb\u5165\u540e\u76f4\u63a5\u70b9\u51fb\u5de6\u4e0a\u89d2\u5151\u6362\u65b0\u4eba0.3\u5143\u7ea2\u5305\uff0c\u79d2\u5230\u8d26\u3002\u3002\n\u8981\u662f\u9ec4\u4e86\u8bc4\u8bba\u533a\u8bb2\u4e00\u4e0b\u6211\u5220\u8d34</p>\n<pre><img alt=\"\uff08\u53e3\u888b\u4fee\u4ed9\uff09\u5fc5\u4e2d\uff01\" src=\"https://osszrbimg.zrb.net/cirheadimg/202106/c0e5f71d-50c8-43fe-942c-ba98f755d6d3400x800.jpg\"/></pre>\n<p></p>\n<pre><img alt=\"\uff08\u53e3\u888b\u4fee\u4ed9\uff09\u5fc5\u4e2d\uff01\" src=\"https://osszrbimg.zrb.net/cirheadimg/202106/751bd92b-d14e-4369-82e0-3d209d107f44400x800.jpg\"/></pre>", "time": 1624548922}, {"title": "\u3010\u5510\u5c71\u75be\u63a7\u3011 \u975e\u5fc5\u4e2d", "content": "<p>\u5fae\u4fe1\u5173\u6ce8\u5510\u5c71\u75be\u63a7\u516c\u4f17\u53f7\uff0c\u83dc\u5355\u680f\u5de6\u8fb9\u5065\u5eb7\u7d20\u517b\u7b54\u989810\u9053\u5168\u5bf9\u62bd\u5956\uff0c\u9898\u96be\uff0c\u53ef\u767e\u5ea6\uff0c\u53ef\u53cd\u590d\u7b54\u9898\u53cd\u590d\u62bd\uff0c\u4e00\u5929\u9650\u4e2d\u4e00\u5305\uff0c5\u5929\u53ef\u4e2d3\u5305\u3002\u6ca1\u8010\u5fc3\u7684\u53ef\u4ee5\u4e0d\u7528\u53bb\u4e86</p>\n<pre><img alt=\"\u3010\u5510\u5c71\u75be\u63a7\u3011 \u975e\u5fc5\u4e2d\" src=\"https://osszrbimg.zrb.net/cirheadimg/202106/c3c8a049-8a8a-49a0-8131-fe17eaa1504d400x800.jpg\"/></pre>\n<p>\u7b2c\u4e8c\u4e2a\u53f7\u4e5f\u4e2d\u4e86\uff0c\u62bd\u4e864\u6b21\u624d\u4e2d\uff0c\u9700\u8981\u70b9\u8010\u5fc3</p>\n<pre><img alt=\"\u3010\u5510\u5c71\u75be\u63a7\u3011 \u975e\u5fc5\u4e2d\" src=\"https://osszrbimg.zrb.net/cirheadimg/202106/6d1130a8-5fc9-407c-85c2-24cae65e11df400x800.jpg\"/></pre>", "time": 1624214159}, {"title": "\uff3b\u534e\u590f\u57fa\u91d1\uff3d\u5fae\u4fe1\u7ea2\u5305 \u975e\u5fc5\u4e2d", "content": "<p><a href=\"https://mp.weixin.qq.com/s/7Qv4vSIhXKhZk8sIYuVpkg\">https://mp.weixin.qq.com/s/7Qv4vSIhXKhZk8sIYuVpkg</a>\n\n\u5fae\u4fe1\u6253\u5f00\u4e0b\u62c9\u9605\u8bfb\u539f\u6587\u7b54\u6848aab </p>\n<pre><img alt=\"\uff3b\u534e\u590f\u57fa\u91d1\uff3d\u5fae\u4fe1\u7ea2\u5305 \u975e\u5fc5\u4e2d\" src=\"https://osszrbimg.zrb.net/cirheadimg/202106/d6efa483-d103-4148-8d48-33ca729d8519400x800.jpg\"/></pre>\n<p></p>\n<pre><img alt=\"\uff3b\u534e\u590f\u57fa\u91d1\uff3d\u5fae\u4fe1\u7ea2\u5305 \u975e\u5fc5\u4e2d\" src=\"https://osszrbimg.zrb.net/cirheadimg/202106/01fc19ee-bdc1-4602-a676-c5d0d6a1a0c2400x800.jpg\"/></pre>", "time": 1624433733}, {"title": "\u3010\u626c\u5dde\u5e02\u573a\u76d1\u7ba1\u5c40\u3011\u5fae\u4fe1\u7ea2\u5305\uff0c\u975e\u5fc5\u4e2d", "content": "<p>\u5fae\u4fe1\u5173\u6ce8\u626c\u5dde\u5e02\u573a\u76d1\u7ba1\u5c40\u56de\u590d\u7b54\u9898\u53c2\u52a0\u6d3b\u52a8\u3002</p>\n<pre><img alt=\"\u3010\u626c\u5dde\u5e02\u573a\u76d1\u7ba1\u5c40\u3011\u5fae\u4fe1\u7ea2\u5305\uff0c\u975e\u5fc5\u4e2d\" src=\"https://osszrbimg.zrb.net/cirheadimg/202106/3a1160d2-e2ba-46da-aa71-f37d3b8928ab400x800.jpg\"/></pre>\n<p></p>\n<pre><img alt=\"\u3010\u626c\u5dde\u5e02\u573a\u76d1\u7ba1\u5c40\u3011\u5fae\u4fe1\u7ea2\u5305\uff0c\u975e\u5fc5\u4e2d\" src=\"https://osszrbimg.zrb.net/cirheadimg/202106/701ecb59-2a2a-48f0-8ccd-f77ed96dff34400x800.jpg\"/></pre>\n<p></p>\n<pre><img alt=\"\u3010\u626c\u5dde\u5e02\u573a\u76d1\u7ba1\u5c40\u3011\u5fae\u4fe1\u7ea2\u5305\uff0c\u975e\u5fc5\u4e2d\" src=\"https://osszrbimg.zrb.net/cirheadimg/202106/99e15bca-227d-4093-a246-9c805b684188400x800.jpg\"/></pre>", "time": 1624548917}, {"title": "\uff08\u53e3\u888b\u4fee\u4ed9\uff09\u5fc5\u4e2d0.3", "content": "<p>\u5fae\u4fe1\u641c\u7d22\u5c0f\u7a0b\u5e8f\uff08\u53e3\u888b\u4fee\u4ed9\uff09\u8fdb\u5165\u540e\u76f4\u63a5\u70b9\u51fb\u5de6\u4e0a\u89d2\u5151\u6362\u65b0\u4eba0.3\u5143\u7ea2\u5305</p>\n<pre><img alt=\"\uff08\u53e3\u888b\u4fee\u4ed9\uff09\u5fc5\u4e2d0.3\" src=\"https://osszrbimg.zrb.net/cirheadimg/202106/2530a3a3-e28b-4c37-9a00-d980951f963e400x800.jpg\"/></pre>\n<p>\u5151\u6362\u79d2\u5230\u8d26</p>\n<pre><img alt=\"\uff08\u53e3\u888b\u4fee\u4ed9\uff09\u5fc5\u4e2d0.3\" src=\"https://osszrbimg.zrb.net/cirheadimg/202106/90b41404-ae42-4e80-912d-d1811160e61c400x800.jpg\"/></pre>", "time": 1624228511}, {"title": "\n\u514d\u8d39\u9886\u53d6 Keep \u5065\u8eab\u8fd0\u52a8\u4f1a\u5458\u5468\u5361 ", "content": "<p><a href=\"https://69fl.cn/wp-content/uploads/2019/09/keep.png\"><img alt=\"\" class=\"alignnone size-full wp-image-6564 img-lazyload\" src=\"https://69fl.cn/wp-content/uploads/2019/09/keep.png\" height=\"376\" loading=\"lazy\"  width=\"750\"/></a></p>\n<p>Keep \u662f\u4e00\u6b3e\u63d0\u4f9b\u5065\u8eab\u6559\u5b66\u3001\u8dd1\u6b65\u3001\u9a91\u884c\u3001\u996e\u98df\u6307\u5bfc\u7b49\u4e00\u7ad9\u5f0f\u8fd0\u52a8\u89e3\u51b3\u65b9\u6848\u7684 App\uff0c\u91cc\u9762\u6709\u5f88\u591a\u953b\u70bc\u8bfe\u7a0b\u514d\u8d39\u89c2\u770b\uff0c\u559c\u6b22\u5065\u8eab\u7684\u53ef\u4ee5\u9886\u4e0b~</p>\n<p>\u6d3b\u52a8\u5730\u5740\uff1a<a href=\"https://mo.gotokeep.com/topic/330310146171351040\" rel=\"noopener\" target=\"_blank\">https://mo.gotokeep.com/topic/330310146171351040</a></p>", "time": 1624147369}, {"title": "\n\u817e\u8baf\u51fa\u884c\u670d\u52a1\u5c0f\u7a0b\u5e8f\u7b7e\u5230\u98861~3\u5143 ", "content": "<p><a href=\"https://69fl.cn/wp-content/uploads/2021/06/6560.jpg\"><img alt=\"\" class=\"alignnone size-full wp-image-6561 img-lazyload\" src=\"https://69fl.cn/wp-content/uploads/2021/06/6560.jpg\" height=\"1425\" loading=\"lazy\"  width=\"1300\"/></a></p>\n<p>\u6ca1\u6709\u4e86\u5c31\u7b2c\u4e8c\u5929\u65e9\u70b9\u6765~</p>\n<p>\u5fae\u4fe1\u5c0f\u7a0b\u5e8f\u641c\u7d22\u201c\u817e\u8baf\u51fa\u884c\u670d\u52a1\u201d-&gt;\u70b9\u5de6\u4e0a\u89d2\u6539\u624b\u52a8\u6210\u201c\u4f5b\u5c71\u5e02\u201d</p>\n<p>\u7136\u540e\u518d\u70b9\u53f3\u4fa7\u8fb9\u7ea2\u5305\u6807\u5fd7-&gt;\u8fdb\u53bb\u5fc5\u987b\u8fde\u7eed\u7b7e\u52303\u5929\u624d\u80fd\u63d0\u73b0\u7ea2\u5305\uff01</p>", "time": 1624184809}, {"title": "\n\u7f8e\u7684\u7f8e\u5c45App\u7535\u8d39\u8865\u8d34\u62bd5\u5143\u7ea2\u5305 ", "content": "<p><a href=\"https://69fl.cn/wp-content/uploads/2021/06/6558.jpg\"><img alt=\"\" class=\"alignnone size-full wp-image-6558 img-lazyload\" src=\"https://69fl.cn/wp-content/uploads/2021/06/6558.jpg\" height=\"933\" loading=\"lazy\"  width=\"1300\"/></a></p>\n<p>\u00a0</p>\n<p>\u9700\u8981\u5bb6\u91cc\u6709\u7f8e\u7684\u8bbe\u5907\u624d\u80fd\u53c2\u52a0\uff01\u5e94\u7528\u5546\u5e97\u4e0b\u8f7d\u7f8e\u7684\u7f8e\u5c45APP-&gt;\u9996\u9875\u4e0a\u9762\u201c\u7535\u8d39\u8865\u8d34\u201d</p>\n<p>\u8fdb\u53bb\u8fde\u7eed\u6bcf\u5929\u7b7e\u5230-&gt;\u4e0b\u62c9\u9875\u9762\u505a\u4efb\u52a1\u8fd8\u80fd\u9886\u968f\u673a\u7ea2\u5305-&gt;\u7d2f\u8ba1\u6ee15\u5143\u5373\u53ef\u63d0\u73b0\u5230\u5fae\u4fe1</p>", "time": 1624184146}, {"title": "\n\u4eac\u4e1c\u90e8\u5206\u7528\u6237\u9886\u4eac\u8c46\u548c\u8fd0\u8d39\u5238 ", "content": "<p><a href=\"https://69fl.cn/wp-content/uploads/2021/06/6553.jpg\"><img alt=\"\" class=\"alignnone size-full wp-image-6554 img-lazyload\" src=\"https://69fl.cn/wp-content/uploads/2021/06/6553.jpg\" height=\"1416\" loading=\"lazy\"  width=\"1300\"/></a></p>\n<p>\u00a0</p>\n<p>\u94fe\u63a5 1 \u6700\u8fd1\u5728\u4eac\u4e1c\u8d85\u5e02\u4e70\u8fc7\u4e1c\u897f\u7684\u5f00\u798f\u888b\u9886\u4eac\u8c46 -&gt; \u94fe\u63a5 2\u30013\u30014 \u76f4\u63a5\u70b9\u9886\u53d6</p>\n<p>\u5168\u54c1\u7c7b 6 \u5143\u65e0\u95e8\u69db\u63d0\u793a\u64e6\u80a9\u5c31\u8bf4\u660e\u6ca1\u8d44\u683c -&gt; \u8fdb\u53bb\u5c31\u663e\u793a\u7acb\u5373\u4f7f\u7528\u8bf4\u660e\u9886\u8fc7\u7c7b\u4f3c\u7684\uff01</p>\n<p>\u00a0</p>\n<h3>\u6d3b\u52a8\u5730\u5740</h3>\n<ol>\n<li><a href=\"https://u.jd.com/GL2CNv2\" rel=\"noopener\" target=\"_blank\">https://u.jd.com/GL2CNv2</a></li>\n<li><a href=\"https://u.jd.com/GM2CvsN\" rel=\"noopener\" target=\"_blank\">https://u.jd.com/GM2CvsN</a></li>\n<li><a href=\"https://u.jd.com/Gw2CSvN\" rel=\"noopener\" target=\"_blank\">https://u.jd.com/Gw2CSvN</a></li>\n<li><a href=\"https://u.jd.com/Gf2CpTx\" rel=\"noopener\" target=\"_blank\">https://u.jd.com/Gf2CpTx</a></li>\n</ol>", "time": 1624182830}, {"title": "\n\u767e\u5ea6\u7f51\u76d8\u7b7e\u5230\u98863~31\u5929\u4f1a\u5458 ", "content": "<p><a href=\"https://69fl.cn/wp-content/uploads/2021/06/6550.jpg\"><img alt=\"\" class=\"alignnone size-full wp-image-6551 img-lazyload\" src=\"https://69fl.cn/wp-content/uploads/2021/06/6550.jpg\" height=\"939\" loading=\"lazy\"  width=\"1300\"/></a></p>\n<p>\u6253\u5f00\u5730\u5740\u70b9\u51fb\u4e00\u952e\u7b7e\u5230-&gt;\u8df3\u8f6c\u5230\u767e\u5ea6\u7f51\u76d8APP-&gt;\u8fde\u7eed\u7b7e\u52307\u5929\u5373\u53ef\u6d3b\u52a8\u6700\u4f4e3\u5929\u767e\u5ea6\u7f51\u76d8\u8d85\u7ea7\u4f1a\u5458</p>\n<p>\u6d3b\u52a8\u5730\u5740\uff1a<a href=\"https://pan.baidu.com/component/view/1836\" rel=\"noopener\" target=\"_blank\">https://pan.baidu.com/component/view/1836</a></p>", "time": 1624181464}, {"title": "\u3010\u987a\u5fb7\u519c\u5546\u3011\u5fae\u4fe1\u96f6\u94b1\u975e\u5fc5\u4e2d", "content": "<p>\u590d\u5236\u94fe\u63a5\u5fae\u4fe1\u6253\u5f00\uff0c\u51e1\u79d1\u76ee\u524d\u9ad8\u51e0\u7387\u4e2d\u5c0f\u6bdb\uff1a<a href=\"https://20880899-247.hdpyqf.com/20880899/KjlkTSV90OiwZ-u96jiCQg/bpb.html?fromQrcode=2WeNXS8Z7GS\">https://20880899-247.hdpyqf.com/20880899/KjlkTSV90OiwZ-u96jiCQg/bpb.html?fromQrcode=2WeNXS8Z7GS</a></p>\n<pre><img alt=\"\u3010\u987a\u5fb7\u519c\u5546\u3011\u5fae\u4fe1\u96f6\u94b1\u975e\u5fc5\u4e2d\" src=\"https://osszrbimg.zrb.net/cirheadimg/202106/644ac2fc-7e4f-49c3-a32b-9e3189a5e053400x800.jpg\"/></pre>", "time": 1624174565}, {"title": "\u3010\u94f6\u534e\u57fa\u91d1\u3011\u7ea2\u5305 \u9650\u91cf\u5fc5\u4e2d", "content": "<p>\u5fae\u4fe1\u5173\u6ce8\u94f6\u534e\u57fa\u91d1\uff0c\u6628\u5929\u63a8\u6587\u7b2c2\u4e2a\uff0c\u6216\u8005\u590d\u5236\u94fe\u63a5\uff0c\u9605\u8bfb\u539f\u6587\uff0c\u9700\u8981\u7528\u624b\u673a\u53f7\u6ce8\u518c\uff0c\u4e0a\u671f\u9886\u8fc7\u7684\u4e0d\u77e5\u9053\u8fd8\u80fd\u4e0d\u80fd\u9886<a href=\"https://mp.weixin.qq.com/s/D9OpF4E-w40yFWGbYi1eWw\">https://mp.weixin.qq.com/s/D9OpF4E-w40yFWGbYi1eWw</a>\uff0c</p>\n<pre><img alt=\"\u3010\u94f6\u534e\u57fa\u91d1\u3011\u7ea2\u5305 \u9650\u91cf\u5fc5\u4e2d\" src=\"https://osszrbimg.zrb.net/cirheadimg/202106/430288ae-1562-4a74-9218-f3cd363c3b62400x800.jpg\"/></pre>", "time": 1624548911}, {"title": "\u3010\u5168\u4e00e\u8bca\u3011\u4e0d\u5fc5\u4e2d", "content": "<p>\u5fae\u4fe1\u641c\u7d22\u5c0f\u7a0b\u5e8f\u5168\u4e00e\u8bca\uff0c\u9996\u9875\u7b2c\u4e00\u6761\u8fdb\u53bb\u4e71\u7b54\u62bd \n\u8fd8\u6709\u673a\u4f1a\u7684\u53bb\u4e0b \u76ee\u524d\u6709\u5927\u5305 </p>\n<pre><img alt=\"\u3010\u5168\u4e00e\u8bca\u3011\u4e0d\u5fc5\u4e2d\" src=\"https://osszrbimg.zrb.net/cirheadimg/202106/429c845f-2714-4fec-81dc-6f87dbd47c9b400x800.jpg\"/></pre>", "time": 1624491312}, {"title": "\u3010\u4eb3\u5dde\u536b\u76d1\u5c40\u3011\u5fae\u4fe1\u96f6\u94b1\u975e\u5fc5\u4e2d", "content": "<p>\u590d\u5236\u94fe\u63a5\u5fae\u4fe1\u6253\u5f00\uff0c\u5047\u51e1\u79d1\u7b54\u9898\u62bd\u5956\uff0c6\u6b21\u673a\u4f1a\u7528\u5b8c\uff0c\u4eb2\u6d4b\u4e00\u53f7\u591a\u5305\uff1a<a href=\"https://20881775-35.hd.webportal.to\">https://20881775-35.hd.webportal.to</a>p/20881775/Fml1laPysxvApMW594Bwug/nldtz.html?style=Ir6LXS5sDUW</p>\n<pre><img alt=\"\u3010\u4eb3\u5dde\u536b\u76d1\u5c40\u3011\u5fae\u4fe1\u96f6\u94b1\u975e\u5fc5\u4e2d\" src=\"https://osszrbimg.zrb.net/cirheadimg/202106/9a874c11-44fb-416d-836c-e885cb187bdf400x800.jpg\"/></pre>\n<p></p>\n<pre><img alt=\"\u3010\u4eb3\u5dde\u536b\u76d1\u5c40\u3011\u5fae\u4fe1\u96f6\u94b1\u975e\u5fc5\u4e2d\" src=\"https://osszrbimg.zrb.net/cirheadimg/202106/6dc298e7-b9c7-44f4-ab23-181a39e9d5a0400x800.jpg\"/></pre>", "time": 1624260939}, {"title": "\u3010\u90ae\u50a8\u94f6\u884c\u5317\u4eac\u5206\u884c\u3011\u7ea2\u5305\u975e\u5fc5\u4e2d", "content": "<p>\u5fae\u4fe1\u6253\u5f00\uff0c\u70b9\u56fe\u8fdb\u53bb\u76f4\u63a5\u62bd\n<a href=\"https://mp.weixin.qq.com/s/ErjcYm6TtK5onfCNZfOE_A\">https://mp.weixin.qq.com/s/ErjcYm6TtK5onfCNZfOE_A</a></p>\n<pre><img alt=\"\u3010\u90ae\u50a8\u94f6\u884c\u5317\u4eac\u5206\u884c\u3011\u7ea2\u5305\u975e\u5fc5\u4e2d\" src=\"https://osszrbimg.zrb.net/cirheadimg/202106/00779004-8e9b-4345-93cc-0e5af29b2258400x800.jpg\"/></pre>\n<p></p>\n<pre><img alt=\"\u3010\u90ae\u50a8\u94f6\u884c\u5317\u4eac\u5206\u884c\u3011\u7ea2\u5305\u975e\u5fc5\u4e2d\" src=\"https://osszrbimg.zrb.net/cirheadimg/202106/1aa8e5ab-b165-47e6-9d79-e95d19634410400x800.jpg\"/></pre>", "time": 1624476912}, {"title": "\u3010\u8054\u60f3\u5546\u57ce\u3011\u4e0d\u5fc5\u4e2d", "content": "<p>\u5fae\u4fe1\u5c0f\u7a0b\u5e8f\u641c\u7d22\u201c\u8054\u60f3\u5546\u57ce+\u201d-&gt;\u9996\u9875\u4e24\u4e2a\u6d3b\u52a8\u8fdb-&gt;\u8bfb\u53e3\u4ee4+\u83b7\u5f97\u5151\u6362\u7801\u62bd-&gt;\u4eb2\u6d4b0.60\u5143\u5fae\u4fe1\u7ea2\u5305\uff01</p>\n<pre><img alt=\"\u3010\u8054\u60f3\u5546\u57ce\u3011\u4e0d\u5fc5\u4e2d\" src=\"https://osszrbimg.zrb.net/cirheadimg/202106/0abf85b4-75a9-4da9-9ec3-8513afeaa4cf400x800.jpg\"/></pre>", "time": 1624390511}, {"title": "\u3010\u6bd4\u7279\u5e01\u5927\u7206\u70b8\u3011\u5fc5\u4e2d", "content": "<p>\u3010\u6bd4\u7279\u5927\u7206\u70b8\u65b0\u7528\u6237\u98863\u5143\u3011\u4e0d\u9700\u8981\u4e0b\u8f7d\u6e38\u620f\uff0c\u5b89\u5353\u7684\u641c\u7d22\u4e0b\u8f7d\u5148\u6e38 APP-&gt;\u7136\u540e\u641c\u7d22\u201c\u6bd4\u7279\u5927\u7206\u70b8\u201d-&gt;\u79d2\u73a9-&gt;\u5fae\u4fe1\u767b\u5f55\u8fdb\u4e0b\u5927\u533a\u5c31\u884c\u4e86-&gt;\u7136\u540e\u5fae\u4fe1\u6253\u5f00\u94fe\u63a5\u9886\u7ea2\u5305!\u82f9\u679c\u7684\u5c31\u8981\u4e0b\u8f7d\u6e38\u620f\n\n\n<a href=\"http://t.cn/A6fhUHx8\">http://t.cn/A6fhUHx8</a>\n\n\u6ca1\u5305\u7684\u8bdd\u665a\u4e0a12\u70b9\u53bb\u9886\u591a\u53f7\u591a\u64b8</p>\n<pre><img alt=\"\u3010\u6bd4\u7279\u5e01\u5927\u7206\u70b8\u3011\u5fc5\u4e2d\" src=\"https://osszrbimg.zrb.net/cirheadimg/202106/16715134-37aa-4072-b124-313bb0950de0400x800.jpg\"/></pre>", "time": 1624340111}, {"title": "\u3010\u653b\u57ce\u77f3\u3011\u7ea2\u5305\u975e\u5fc5\u4e2d", "content": "<p>\u9996\u5148\u5173\u6ce8\u201c\u653b\u57ce\u77f3\u201d\u516c\u4f17\u53f7\n\u7136\u540e\u5fae\u4fe1\u6253\u5f00\u94fe\u63a5\uff0c\u4e0d\u4e2d\u53cd\u590d\n<a href=\"https://mp.weixin.qq.com/s/nueeE2i2eX7xCY_z4-A-NQ\">https://mp.weixin.qq.com/s/nueeE2i2eX7xCY_z4-A-NQ</a></p>\n<pre><img alt=\"\u3010\u653b\u57ce\u77f3\u3011\u7ea2\u5305\u975e\u5fc5\u4e2d\" src=\"https://osszrbimg.zrb.net/cirheadimg/202106/598d502c-4a5c-4078-9ead-776d9cd79f1f400x800.jpg\"/></pre>\n<p></p>\n<pre><img alt=\"\u3010\u653b\u57ce\u77f3\u3011\u7ea2\u5305\u975e\u5fc5\u4e2d\" src=\"https://osszrbimg.zrb.net/cirheadimg/202106/8a196c41-bc29-4c59-b07a-7c37cb3bde3f400x800.jpg\"/></pre>", "time": 1624322111}, {"title": "\n\u6bd4\u7279\u5927\u7206\u70b8\u65b0\u73a9\u5bb6\u98863\u5143\u5fae\u4fe1\u7ea2\u5305 ", "content": "<p><a href=\"https://69fl.cn/wp-content/uploads/2021/06/6530.png\"><img alt=\"\" class=\"alignnone size-full wp-image-6531 img-lazyload\" src=\"https://69fl.cn/wp-content/uploads/2021/06/6530.png\" height=\"889\" loading=\"lazy\"  width=\"1000\"/></a></p>\n<p>\u00a0</p>\n<div class=\"title-plane\"><p>\u7b80\u5355\u7c97\u66b4\u5fc5\u4e2d\uff0c2\u5206\u949f\u641e\u5b9a\u3002</p><div>\u5b89\u5353\u7684\u4e0d\u9700\u8981\u4e0b\u8f7d\u672c\u8eab\u6e38\u620f\uff0c\u76f4\u63a5\u4e91\u6e38\u620f\u3002", "time": 1624082099}, {"title": "\u3010\u9886\u5b8c\u7ea2\u5305\u53d6\u6d88\u5173\u6ce8\u3011\u5fc5\u4e2d", "content": "<p><a href=\"https://mp.weixin.qq.com/s/BhZZ4rq409PkDVppBddSIQ\">https://mp.weixin.qq.com/s/BhZZ4rq409PkDVppBddSIQ</a>\n\n\u5173\u6ce8\u516c\u4f17\u53f7\u6309\u6b65\u9aa4\u6765\u6536\u85cf\u8f6c\u53d1\u5230\u516c\u4f17\u53f7\uff0c\u8bb0\u5f97\u5f04\u5b8c\u76f4\u63a5\u53d6\u6d88\u5173\u6ce8\u4e0d\u8981\u9017\u7559\n\n\u9886\u5b8c\u7ea2\u5305\u8bb0\u5f97\u53d6\u6d88\u5173\u6ce8\n\n\u6628\u5929\u53d1\u7684\u8fc7\u671f\u4e86\u91cd\u65b0\u8865\u53d1\u4e00\u6761\u6ca1\u73a9\u7684\u53bb\n\u6628\u5929\u73a9\u8fc7\u5c31\u4e0d\u8981\u53bb\u4e86</p>\n<pre><img alt=\"\u3010\u9886\u5b8c\u7ea2\u5305\u53d6\u6d88\u5173\u6ce8\u3011\u5fc5\u4e2d\" src=\"https://osszrbimg.zrb.net/cirheadimg/202106/c3350f58-0867-4dcb-8f21-ba62190580fd400x800.jpg\"/></pre>", "time": 1624005365}, {"title": "\n\u6dd8\u5b9d\u9080\u8bf7\u5165\u4f1a\u514d\u8d39\u64b8\u5929\u732b\u7cbe\u7075\u65b9\u7cd6R ", "content": "<p>\u5b9d\u8d1d\u731c\u731c\u65d7\u8230\u5e97\u9080\u8bf7\u597d\u53cb\u5165\u4f1a\u514d\u8d39\u64b8\u5929\u732b\u7cbe\u7075\u65b9\u7cd6R\u3001\u624b\u94fe\u3001\u624b\u8868\u7b49\uff0c\u9700\u8981\u4e24\u4e2a\u6dd8\u5b9d\u53f7\uff08\u4e0d\u540c\u624b\u673a\u53f7\uff09\uff0c\u4e3b\u53f7\u505a\u6d3b\u52a8\uff0c\u526f\u53f7\u5237\u52a9\u529b\u3002</p>\n<p>\u00a0</p>\n<p>\u4e3b\u8981\u5229\u7528\u4e86\u300c\u5165\u4f1a\u52a9\u529b\u300d\u4e4b\u540e\u9000\u4f1a\u518d\u901a\u8fc7\u9080\u8bf7\u94fe\u63a5\u5165\u4f1a\uff0c\u8fd9\u6837\u5b50\u4e5f\u662f\u8bb0\u52a9\u529b\u6b21\u6570\u7684\uff0c\u91cd\u590d70\u6b21\u5373\u53ef\uff0c\u64cd\u4f5c\u5f97\u5feb\u53ea\u9700\u8981\u5341\u591a\u5206\u949f\u3002</p>\n<p>\u00a0</p>\n<h3>\u4e3b\u53f7\u53c2\u5165\u6d3b\u52a8</h3>\n<p>\u00a0</p>\n<p>\u590d\u5236\u6dd8\u53e3\u4ee4\u300c8 ha:/\u00a5hslsXhxfv76\u00a3\u300d\u6253\u5f00\u6dd8\u5b9dApp\u8fdb\u5165\u6d3b\u52a8\u9875\uff0c\u5982\u56fe\u64cd\u4f5c\u5165\u4f1a\u540e\u70b9\u51fb\u7acb\u5373\u9080\u8bf7\uff08\u590d\u5236\u5f97\u5230\u7684\u9080\u8bf7\u94fe\u63a5\u5907\u7528\uff09\uff1a</p>\n<p>\u00a0</p>\n<p><a href=\"https://69fl.cn/wp-content/uploads/2021/06/6514-1.png\"><img alt=\"\" class=\"alignnone size-full wp-image-6518 img-lazyload\" src=\"https://69fl.cn/wp-content/uploads/2021/06/6514-1.png\" height=\"889\" loading=\"lazy\"  width=\"2000\"/></a></p>\n<p>\u00a0</p>\n<h3>\u526f\u53f7\u5237\u52a9\u529b</h3>\n<p>\u00a0</p>\n<p>\u6dd8\u5b9dApp\u5207\u6362\u5230\u7b2c\u4e8c\u4e2a\u53f7\uff0c\u6253\u5f00\u4e3b\u53f7\u7684\u9080\u8bf7\u52a9\u529b\u9875\u9762\uff08\u6dd8\u53e3\u4ee4\u6216\u8005\u7f51\u5740\u8df3\u8f6c\uff09\u3002</p>\n<p>\u00a0</p>\n<div class=\"c-alert\"><i class=\"far fa-info-circle\"></i>\u63a8\u8350\u7528\u6d4f\u89c8\u5668\u6253\u5f00\u94fe\u63a5\u8df3\u8f6c\uff0c\u4e0d\u7528\u4e00\u76f4\u590d\u5236\u6dd8\u53e3\u4ee4\uff0c\u7279\u522b\u662f\u6709\u65f6\u5019\u6dd8\u53e3\u4ee4\u8fd8\u65e0\u6cd5\u8bc6\u522b\uff01</div>\n<p>\u00a0</p>\n<div class=\"title-plane\"><p>\u6253\u5f00\u9080\u8bf7\u52a9\u529b\u9875\u9762\u4e4b\u540e\u7684\u6d6e\u7a97\u5168\u90e8\u00d7\u6389\uff01</p><div>\u4e0d\u8981\u70b9\u300c\u7acb\u5373\u52a9\u529b\u300d\uff01\u4e0d\u9700\u8981\u70b9\u300c\u7acb\u5373\u52a9\u529b\u300d\uff01", "time": 1623990307}, {"title": "\u3010ASUS\u534e\u7855\u5546\u57ce\u3011 \u975e\u5fc5\u4e2d", "content": "<p>\u5173\u6ce8\u516c\u4f17\u53f7\uff0c\u7ffb\u724c\u6709\u5956<a href=\"https://25379339-78.hd.faisco.cn/25379339/47wL3-0HZaiI76uK2CkxFA/jrdpd.html?editQrcode=true&amp;_source=1&amp;fromImgMsg=true&amp;canal=-1\">https://25379339-78.hd.faisco.cn/25379339/47wL3-0HZaiI76uK2CkxFA/jrdpd.html?editQrcode=true&amp;_source=1&amp;fromImgMsg=true&amp;canal=-1</a></p>\n<pre><img alt=\"\u3010ASUS\u534e\u7855\u5546\u57ce\u3011 \u975e\u5fc5\u4e2d\" src=\"https://osszrbimg.zrb.net/cirheadimg/202106/f0ec2214-3961-437e-a9eb-829c9bbd31a4400x800.jpg\"/></pre>", "time": 1623962166}, {"title": "\u3010\u9886\u5b8c\u7ea2\u5305\u9a6c\u4e0a\u53d6\u5173\u3011\u5fc5\u4e2d", "content": "<p><a href=\"https://mp.weixin.qq.com/s/BhZZ4rq409PkDVppBddSIQ\">https://mp.weixin.qq.com/s/BhZZ4rq409PkDVppBddSIQ</a>\n\n\u5173\u6ce8\u516c\u4f17\u53f7\u6309\u6b65\u9aa4\u6765\u6536\u85cf\u8f6c\u53d1\u5230\u516c\u4f17\u53f7\uff0c\u8bb0\u5f97\u5f04\u5b8c\u76f4\u63a5\u53d6\u6d88\u5173\u6ce8\u4e0d\u8981\u9017\u7559\n\n\u9886\u5b8c\u7ea2\u5305\u8bb0\u5f97\u9a6c\u4e0a\u53d6\u5173</p>\n<pre><img alt=\"\u3010\u9886\u5b8c\u7ea2\u5305\u9a6c\u4e0a\u53d6\u5173\u3011\u5fc5\u4e2d\" src=\"https://osszrbimg.zrb.net/cirheadimg/202106/0dafbb23-e8a8-449b-940f-40e3f10c3107400x800.jpg\"/></pre>", "time": 1623918965}, {"title": "\n\u6dd8\u5b9d\u5e97\u94fa\u5165\u4f1a\u9886\u53d65\u5143\u7ea2\u5305 ", "content": "<p><a href=\"https://69fl.cn/wp-content/uploads/2021/06/6504.jpg\"><img alt=\"\" class=\"alignnone size-full wp-image-6505 img-lazyload\" src=\"https://69fl.cn/wp-content/uploads/2021/06/6504.jpg\" height=\"910\" loading=\"lazy\"  width=\"1755\"/></a></p>\n<p>\u7b80\u5355\u5fc5\u4e2d\uff0c5\u4e2a\u5e97\u94fa\u54041\u5143</p>\n<ol>\n<li>\u624b\u673a\u6dd8\u5b9d\u4f9d\u6b21\u641c\u7d22\u201c\u9ad8\u901a\u9a81\u9f99\u65d7\u8230\u5e97\u201d\u3001\u201c\u4e00\u52a0\u65d7\u8230\u5e97\u201d\u3001\u201cOPPO\u65d7\u8230\u5e97\u201d\u3001\u201c\u5361\u8428\u5e1d\u65d7\u8230\u5e97\u201d\u3001\u201c3CE\u65d7\u8230\u5e97\u201d-&gt;\u8fdb\u5e97</li>\n<li>\u9ad8\u901a\u7684\u70b9\u9996\u9875\u4e2d\u95f4\u52a0\u5165\u9a81\u9f99\u9886\u4e00\u52a0\u7684\u70b9\u9996\u9875\u4e2d\u95f460000\u9886\u53d6\uff0cOPPO\u7684\u70b9\u9996\u9875\u5165\u4f1a\u74dc\u5206\u9886\u53d6\uff0c\u5361\u8428\u5e1d\u7684\u70b9\u53f3\u4e0b\u89d2\u5e97\u94fa\u4f1a\u5458</li>\n<li>\u4e0b\u62c9\u5151\u6362\u7ea2\u5305-&gt;\u6ca1\u79ef\u5206\u4e0a\u6ed1\u9875\u9762\u5230\u6635\u79f0\u90a3\u91cc-&gt;\u70b9\u4e2d\u95f4\u201c\u5361\u8428\u5e1d\u5f00\u542f \u7467\u4eab\u835f \u7acb\u5373\u5165\u4f1a\u201d-&gt;\u4e0b\u62c9\u9875\u9762-&gt;\u62fc\u56fe\u5f97\u79ef\u5206\u5728\u8fd4\u56de\u5151\u6362\uff013CE\u7684\u70b9\u53f3\u4e0b\u89d2\u5e97\u94fa\u4f1a\u5458\u4e0b\u62c9\u9875\u9762\u5151\u6362\u7ea2\u5305</li>\n</ol>\n<p>PS\uff1a\u90e8\u5206\u5e97\u94fa\u4e0d\u662f\u65b0\u4eba\u9886\u4e0d\u4e86\u5c31\u6362\u4e00\u4e2a\uff01\u5982\u679c\u9886\u7ea2\u5305\u9875\u9762\u663e\u793a\u62a2\u5149\u4e86\u5c31\u522b\u5165\u4f1a\u4e86\uff01\u9886\u4e86\u540e\u70b9\u5e97\u94fa\u4f1a\u5458\uff0c\u518d\u70b9\u5de6\u4e0a\u89d2\u6635\u79f0\uff0c\u4e0b\u62c9\u9875\u9762\u9000\u51fa\u4f1a\u5458\u5373\u53ef\uff01</p>", "time": 1623900949}, {"title": "[\u5efa\u4fe1\u57fa\u91d1]  \u62bd\u5956\u975e\u5fc5\u4e2d", "content": "<p>\u5fae\u4fe1\u5173\u6ce8\u516c\u4f17\u53f7\u3002[\u5efa\u4fe1\u57fa\u91d1]\u53ef\u4ee5\u9605\u8bfb\u539f\u6587\u8fdb\u53bb\u3002\u4e5f\u53ef\u4ee5\u76f4\u63a5\u8f93\u5165  \u517b\u8001  \u4e24\u4e2a\u5b57\u3002\u8fdb\u5165\u62bd\u5956\u9875\u9762\u62bd\u5956\uff0c\u5927\u5bb6\u53bb\u8bd5\u8bd5\u624b\u6c14\u5427\u3002</p>\n<pre><img alt=\"[\u5efa\u4fe1\u57fa\u91d1]  \u62bd\u5956\u975e\u5fc5\u4e2d\" src=\"https://osszrbimg.zrb.net/cirheadimg/202106/a8d96526-9576-4ae4-aa18-f009e8eb6805400x800.jpg\"/></pre>", "time": 1623904567}, {"title": "\u3010\u5efa\u4fe1\u57fa\u91d1\u3011\u4e0d\u5fc5\u4e2d", "content": "<p>\u5fae\u4fe1\u5173\u6ce8\u516c\u4f17\u53f7:\u5efa\u4fe1\u57fa\u91d1\n\u56de\u590d:\u517b\u8001 \n\u63a8\u6587\u8fdb\u5165\u76f4\u63a5\u62bd \u5feb\u5feb\u5feb\u521a\u4e2d</p>\n<pre><img alt=\"\u3010\u5efa\u4fe1\u57fa\u91d1\u3011\u4e0d\u5fc5\u4e2d\" src=\"https://osszrbimg.zrb.net/cirheadimg/202106/97deb91b-ca0e-4673-84ff-bade94f8e0b9400x800.jpg\"/></pre>", "time": 1623897365}, {"title": "\u3010\u6d59\u6c5f\u798f\u5f69\u3011\u4e0d\u5fc5\u4e2d", "content": "<p>\u5fae\u4fe1\u5173\u6ce8\uff1a\u6d59\u6c5f\u798f\u5f69\n\u4e2d\u4e00\u514d\u8d39\u8bd5\u73a9\u8fdb\u53bb \u673a\u4f1a\u7528\u5b8c\n\u4e71\u900910\u4e2a\u4e00\u53f7\u591a\u5305 \u770b\u8138\u6709\u5927</p>\n<pre><img alt=\"\u3010\u6d59\u6c5f\u798f\u5f69\u3011\u4e0d\u5fc5\u4e2d\" src=\"https://osszrbimg.zrb.net/cirheadimg/202106/3a8608a6-949f-4051-87f6-fee30a6364b0400x800.jpg\"/></pre>", "time": 1624296912}, {"title": "\u3010\u62db\u5546\u4fe1\u8bfa\u3011\u5fc5\u4e2d", "content": "<p>\u5fae\u4fe1\u5173\u6ce8\uff1a\u62db\u5546\u4fe1\u8bfa\n\u56de\u590d\uff1a\u4e00\u8bfa\u4e07\u91d1\uff0c\u593a\u5b9d\uff0c\u7ea2\u5305\u6765\u4e86\uff0c\u7ea2\u5305168  \u7ea2\u5305\n\u4e94\u4e2a\u53e3\u4ee4\u90fd\u53bb\u8bd5\u8bd5 \u4e24\u4e2a\u662f\u65b0\u7684 \u8001\u7528\u6237\u4e5f\u53bb      \n\n\u5f04\u5b8c\u53d6\u5173\u4e0b\u6b21\u8fd8\u80fd\u73a9</p>\n<pre><img alt=\"\u3010\u62db\u5546\u4fe1\u8bfa\u3011\u5fc5\u4e2d\" src=\"https://osszrbimg.zrb.net/cirheadimg/202106/088e5b03-6571-46b5-a154-6ae1ca56d01a400x800.jpg\"/></pre>", "time": 1623890160}, {"title": " \u52a0\u4eba\u5fc5\u4e2d", "content": "<p>\u5fae\u4fe1\u626b\u7801\u6dfb\u52a0\u5fae\u4fe1\u63a8\u6587</p>\n<pre><img alt=\" \u52a0\u4eba\u5fc5\u4e2d\" src=\"https://osszrbimg.zrb.net/cirheadimg/202106/8bdc24cd-cc4e-4c7c-bb32-80dd8db160fc400x800.jpg\"/></pre>", "time": 1623882965}, {"title": "\u3010\u6613\u8f66\u7cbe\u9009\u3011\u5fae\u4fe1\u7ea2\u5305\u975e\u5fc5\u4e2d", "content": "<p>\u5fae\u4fe1\u6253\u5f00\u94fe\u63a5\uff0c\u70b9\u56fe\uff0c\u7ea2\u5305\u975e\u5fc5\u4e2d\uff1a<a href=\"https://mp.weixin.qq.com/s/PeZVEU2S0M3hHXnZXFj6iw\">https://mp.weixin.qq.com/s/PeZVEU2S0M3hHXnZXFj6iw</a></p>\n<pre><img alt=\"\u3010\u6613\u8f66\u7cbe\u9009\u3011\u5fae\u4fe1\u7ea2\u5305\u975e\u5fc5\u4e2d\" src=\"https://osszrbimg.zrb.net/cirheadimg/202106/98090308-382f-4d94-b207-8d591d883782400x800.jpg\"/></pre>", "time": 1624088122}, {"title": "\u3010\u5b89\u6155\u5e0c\u3011\u5fc5\u4e2d", "content": "<p><a href=\"https://mp.weixin.qq.com/s/5TUyAtjXHB37Y7QcFsKvRw\">https://mp.weixin.qq.com/s/5TUyAtjXHB37Y7QcFsKvRw</a>\n\n\u5fae\u4fe1\u6253\u5f00\u6388\u6743\u5b8c\u6210\u67e5\u770b\u8d26\u672c\u8bb0\u5f55\u5fc5\u4e2d0.8\u4e0d\u79d2\u63a8\u7b49\u63a8</p>\n<pre><img alt=\"\u3010\u5b89\u6155\u5e0c\u3011\u5fc5\u4e2d\" src=\"https://osszrbimg.zrb.net/cirheadimg/202106/738a0e5d-5cd9-46a9-9b27-c23b56f6ef3c400x800.jpg\"/></pre>", "time": 1623821767}, {"title": "\u3010\u653b\u57ce\u77f3\u3011\u7ea2\u5305 \u975e\u5fc5\u4e2d", "content": "<p>\u653b\u57ce\u77f3\u516c\u4f17\u53f7\u6700\u65b0\u63a8\u6587\u7b2c\u4e00\u4e2a<a href=\"https://h5.amo9.com/h5/2021/june/counting/22/index.html?openId=oc5BOww0W7ZM92IqCVUp5YRqFIs4\">https://h5.amo9.com/h5/2021/june/counting/22/index.html?openId=oc5BOww0W7ZM92IqCVUp5YRqFIs4</a></p>\n<pre><img alt=\"\u3010\u653b\u57ce\u77f3\u3011\u7ea2\u5305 \u975e\u5fc5\u4e2d\" src=\"https://osszrbimg.zrb.net/cirheadimg/202106/8d26385e-7153-40d0-8b62-df74310c6e37400x800.jpg\"/></pre>", "time": 1623818166}, {"title": "\n\u4eac\u4e1c\u9886\u53d6150\u5143\u548c50\u5143\u5168\u54c1\u5238 ", "content": "<p><a href=\"https://69fl.cn/wp-content/uploads/2021/06/6481.jpg\"><img alt=\"\" class=\"alignnone size-full wp-image-6483 img-lazyload\" src=\"https://69fl.cn/wp-content/uploads/2021/06/6481.jpg\" height=\"931\" loading=\"lazy\"  width=\"1300\"/></a></p>\n<p>150\u5143\u5238\u9650\u4eac\u4e1c\u4f1a\u5458\u9886\uff0c50\u5143\u5238\u4eba\u4eba\u90fd\u53ef\u4ee5\u9886</p>\n<p>1\u3001\u5fae\u4fe1\u6253\u5f00-&gt;2000-150\u5143\u5238\u70b9\u4e2d\u95f4\u6700\u9ad8150\u5143\u4f18\u60e0\u5238-&gt;\u9a6c\u4e0a\u62a2-&gt;800-50\u5143\u5238\u70b9\u53f3\u8fb950\u5168\u54c1\u7c7b</p>\n<p>2\u3001\u5c31\u662f\u5728\u4eac\u4e1c\u4e702000\u7684\u4e1c\u897f\u51cf150\u5143\u548c\u4e70800\u7684\u4e1c\u897f\u51cf50-&gt;\u965016\u65e5~18\u65e5\u4e4b\u95f4\u4f7f\u7528-&gt;\u521a\u9700\u76f4\u63a5\u9886</p>\n<p>2000-150\u5168\u54c1\u5238\uff1a<a href=\"https://u.jd.com/GTdp94J\" rel=\"noopener\" target=\"_blank\">https://u.jd.com/GTdp94J</a></p>\n<p>800-50\u5168\u54c1\u5238\uff1a<a href=\"https://u.jd.com/Gpd3PcL\" rel=\"noopener\" target=\"_blank\">https://u.jd.com/Gpd3PcL</a></p>", "time": 1623843177}, {"title": "\u3010\u6cb3\u5317ipTV\u4f1a\u5458\u3011\u73b0\u5728\u5fc5\u4e2d", "content": "<p>\u5fae\u4fe1\u5173\u6ce8\uff1a\u6cb3\u5317IPTV\u4f1a\u5458\n\u83dc\u5355\u680f\u4e2d\u4e0a \u4e00\u53f7\u4e24\u5305\u901f\u5ea6 </p>\n<pre><img alt=\"\u3010\u6cb3\u5317ipTV\u4f1a\u5458\u3011\u73b0\u5728\u5fc5\u4e2d\" src=\"https://osszrbimg.zrb.net/cirheadimg/202106/95c52b4a-3887-462e-b51e-e06d2fe758e9400x800.jpg\"/></pre>", "time": 1623814565}, {"title": "\n\u4eac\u4e1c\u5b66\u751f1\u5143\u64b81\u4e2a\u6708\u7f51\u6613\u4e91 ", "content": "<p><a href=\"https://69fl.cn/wp-content/uploads/2021/06/6478.jpg\"><img alt=\"\" class=\"alignnone size-full wp-image-6479 img-lazyload\" src=\"https://69fl.cn/wp-content/uploads/2021/06/6478.jpg\" height=\"1444\" loading=\"lazy\"  width=\"1300\"/></a></p>\n<p>\u9650\u4eac\u4e1c\u5b66\u751f\u53c2\u52a0</p>\n<p>\u6253\u5f00\u5730\u5740\u70b9\u51fb\u9875\u97629\u6ee110\u53ef\u7528\u5238-&gt;\u7136\u540e\u4f7f\u7528\u8d2d\u4e70\u5373\u53ef-&gt;\u53ef1\u5143\u64b81\u4e2a\u6708\u7f51\u6613\u4e91\u97f3\u4e50\u4f1a\u5458\u7b49\u7b49\u3002</p>\n<p>PS\uff1a\u5982\u679c\u6253\u5f00\u5730\u5740\u6ca1\u770b\u89c1\u6bcf\u65e5\u5fc5\u62a29\u5143\u5238\uff0c\u8bf4\u660e\u6ca1\u4e86\uff0c\u90e8\u5206\u53f7\u4e0d\u80fd\u9886\u4f1a\u63d0\u793a\u706b\u7206</p>\n<p>\u6d3b\u52a8\u5730\u5740\uff1a<a href=\"https://young.m.jd.com/\" rel=\"noopener\" target=\"_blank\">https://young.m.jd.com/</a></p>", "time": 1623838514}, {"title": "\u3010OPPO\u65d7\u8230\u5e97\u3011\u5fc5\u9886\u901a\u7528\u7ea2\u5305", "content": "<p>\u6d3b\u52a8\u2460\u6253\u5f00\u94fe\u63a5\u8fdb\u5165\u6dd8\u5b9d-&gt;\u9996\u9875\u6a2a\u5e45\u5165\u4f1a\u9650\u91cf\u9886\u53d6-&gt;\u7ebf\u4e0a\u7ebf\u4e0b\u90fd\u53ef\u4ee5\u62b5\u6263\u4f7f\u7528\uff1a<a href=\"https://m.tb.cn/h.4EO5Orv\">https://m.tb.cn/h.4EO5Orv</a>\n\n\u6d3b\u52a8\u2461\u6253\u5f00\u94fe\u63a5\u8fdb\u5165\u6dd8\u5b9d-&gt;\u5e95\u90e8\u5e97\u94fa\u4f1a\u5458-&gt;\u65b0\u4eba\u5165\u4f1a\u5f97\u79ef\u5206-&gt;\u4e0b\u62c9\u5151\u6362\u79d2\u5230\u5361\u5305\uff1a<a href=\"https://m.tb.cn/h.4vJpVVo\">https://m.tb.cn/h.4vJpVVo</a></p>\n<pre><img alt=\"\u3010OPPO\u65d7\u8230\u5e97\u3011\u5fc5\u9886\u901a\u7528\u7ea2\u5305\" src=\"https://osszrbimg.zrb.net/cirheadimg/202106/c9f23c16-d84a-4c42-9d01-7ccef00081c1400x800.jpg\"/></pre>\n<p></p>\n<pre><img alt=\"\u3010OPPO\u65d7\u8230\u5e97\u3011\u5fc5\u9886\u901a\u7528\u7ea2\u5305\" src=\"https://osszrbimg.zrb.net/cirheadimg/202106/11bf1a7a-ac21-435f-a6de-ce7776ae10ff400x800.jpg\"/></pre>\n<p></p>\n<pre><img alt=\"\u3010OPPO\u65d7\u8230\u5e97\u3011\u5fc5\u9886\u901a\u7528\u7ea2\u5305\" src=\"https://osszrbimg.zrb.net/cirheadimg/202106/f543cd10-3e8c-4aa4-9771-9e4520d51291400x800.jpg\"/></pre>", "time": 1624206916}, {"title": "\u3010\u6bcf\u5929\u4e00\u5802\u73e0\u5b9d\u8bfe\u3011\u4e0d\u5fc5\u4e2d", "content": "<p>\u2460\u5fae\u4fe1-\u6211\u7684-\u6539\u6027\u522b\uff1a\u5973\n\u5982\u56fe-\u66f4\u591a-\u7136\u540e\u7b492\u5206\u949f\n\u2461\u5173\u6ce8:\u6bcf\u5929\u4e00\u5802\u73e0\u5b9d\u8bfe\n\u63a8\u6587\u8fdb\u5165-\u8ba4\u771f\u770b\u89c6\u9891-\u7b54\u9898\n\u8ba4\u771f\u770b \u89c6\u9891\u91cc\u6709\u7b54\u6848 \u6709\u5927\u5305\uff01\n-\n\u6ca1\u73a9\u8fc7\u7684\u5168 \u8c8c\u4f3c\u5168\u662f\u5927\u5305\u554a\uff5e\n\n\u8bb0\u5f97\u9650\u5973\u6027</p>\n<pre><img alt=\"\u3010\u6bcf\u5929\u4e00\u5802\u73e0\u5b9d\u8bfe\u3011\u4e0d\u5fc5\u4e2d\" src=\"https://osszrbimg.zrb.net/cirheadimg/202106/73748ae7-c4d4-47d4-85c7-e286c089c875400x800.jpg\"/></pre>", "time": 1624206911}]